what_am_i_doing/__init__.py
what_am_i_doing/__main__.py
what_am_i_doing/conf.py
what_am_i_doing/example-todo.txt
what_am_i_doing/new_task_dialog.py
what_am_i_doing/runner.sh
what_am_i_doing/session_options.py
what_am_i_doing/sessions.csv
what_am_i_doing/settings.py
what_am_i_doing/styles.css
what_am_i_doing/task_window.py
what_am_i_doing/utils.py
what_am_i_doing/connectors/activitywatch.py
what_am_i_doing/connectors/caldav.py
what_am_i_doing/connectors/csv.py
what_am_i_doing/connectors/psc_timetracker.py
what_am_i_doing/connectors/taskwarrior.py
what_am_i_doing/connectors/timewarrior.py
what_am_i_doing/connectors/todo_template.py
what_am_i_doing/connectors/todotxt.py
what_am_i_doing/connectors/txt.py
what_am_i_doing/connectors/vikunja.py
what_am_i_doing/icon/cancel.png
what_am_i_doing/icon/cancel.svg
what_am_i_doing/icon/edit.png
what_am_i_doing/icon/edit.svg
what_am_i_doing/icon/icon-0.png
what_am_i_doing/icon/icon-0.svg
what_am_i_doing/icon/icon-1.svg
what_am_i_doing/icon/icon-2.svg
what_am_i_doing/icon/icon-3.svg
what_am_i_doing/icon/icon-4.svg
what_am_i_doing/icon/icon-5.svg
what_am_i_doing/icon/icon-6.svg
what_am_i_doing/icon/icon-7.svg
what_am_i_doing/icon/icon-8.svg
what_am_i_doing/icon/icon-9.svg
what_am_i_doing/icon/icon.png
what_am_i_doing/icon/icon.svg
what_am_i_doing/icon/mark-done.png
what_am_i_doing/icon/mark-done.svg
what_am_i_doing/icon/pause.png
what_am_i_doing/icon/pause.svg
what_am_i_doing/icon/settings.png
what_am_i_doing/icon/settings.svg
what_am_i_doing/icon/unused/action-unavailable-symbolic.svg
what_am_i_doing/icon/unused/applications-engineering-symbolic.svg
what_am_i_doing/icon/unused/background-selected-symbolic.svg
what_am_i_doing/icon/unused/cancel-operation-symbolic.svg
what_am_i_doing/icon/unused/checkbox-checked-symbolic (2).svg
what_am_i_doing/icon/unused/checkbox-checked-symbolic.svg
what_am_i_doing/icon/unused/checkbox-mixed-symbolic (2).svg
what_am_i_doing/icon/unused/checkbox-mixed-symbolic.svg
what_am_i_doing-0.0.8.dist-info/licenses/LICENSE
what_am_i_doing-0.0.8.dist-info/METADATA
what_am_i_doing-0.0.8.dist-info/WHEEL
what_am_i_doing-0.0.8.dist-info/entry_points.txt
what_am_i_doing-0.0.8.dist-info/top_level.txt
what_am_i_doing-0.0.8.dist-info/RECORD
