Metadata-Version: 2.4
Name: what_am_i_doing
Version: 0.0.8
Summary: What am I doing: the open source task-tracking self-control panel.
Author: GitFr33
Project-URL: Homepage, https://gitlab.com/GitFr33/what-am-i-doing
Classifier: Programming Language :: Python :: 3
Classifier: Operating System :: OS Independent
Classifier: License :: OSI Approved :: GNU General Public License v3 or later (GPLv3+)
Classifier: Environment :: X11 Applications :: GTK
Classifier: Intended Audience :: End Users/Desktop
License-File: LICENSE
Requires-Dist: psutil
Requires-Dist: pygobject==3.50.0
Requires-Dist: pycairo==1.27
Requires-Dist: meson
Requires-Dist: meson-python
Requires-Dist: attrs
Requires-Dist: caldav
Requires-Dist: certifi
Requires-Dist: charset-normalizer
Requires-Dist: dbus-idle
Requires-Dist: dbus-python
Requires-Dist: icalendar
Requires-Dist: idna
Requires-Dist: jeepney
Requires-Dist: kitchen
Requires-Dist: lxml
Requires-Dist: playsound3
Requires-Dist: python-dateutil
Requires-Dist: pytodotxt
Requires-Dist: pytz
Requires-Dist: recurring-ical-events
Requires-Dist: requests
Requires-Dist: setproctitle
Requires-Dist: setuptools
Requires-Dist: six
Requires-Dist: taskw
Requires-Dist: timew
Requires-Dist: tzlocal
Requires-Dist: urllib3
Requires-Dist: vobject
Requires-Dist: x-wr-timezone
Dynamic: license-file
